pooledMySQL.py
pooledMySQL-4.0.2.dist-info/METADATA
pooledMySQL-4.0.2.dist-info/WHEEL
pooledMySQL-4.0.2.dist-info/top_level.txt
pooledMySQL-4.0.2.dist-info/RECORD
