Metadata-Version: 2.2
Name: pooledMySQL
Version: 4.0.2
Summary: A simple way to have MySQL connection pool which auto-scales infinitely as required. This would help remove problems caused by multithreading, also removed user hassle of manually creating and deleting connections manually.
Author-email: Bhindi <bhaskarpanja93@gmail.com>
Project-URL: Homepage, https://github.com/BhaskarPanja93/pooledMySQL
Keywords: mysql,pool,threadedmysql,pooledmysql,multithreaded,thread,database,sql
Classifier: License :: OSI Approved :: MIT License
Classifier: Programming Language :: Python
Classifier: Programming Language :: Python :: 3
Requires-Python: >=3.6
Requires-Dist: mysql_connector_python
Requires-Dist: customisedLogs
